chemicalmotifidentifier/__init__.py
chemicalmotifidentifier/_src/__init__.py
chemicalmotifidentifier/_src/correlations.py
chemicalmotifidentifier/_src/dataset.py
chemicalmotifidentifier/_src/dissimilarity.py
chemicalmotifidentifier/_src/frameworks_base.py
chemicalmotifidentifier/_src/ml.py
chemicalmotifidentifier/_src/models.py
chemicalmotifidentifier/_src/plot.py
chemicalmotifidentifier/_src/shell_information.py
chemicalmotifidentifier/_src/transforms.py
chemicalmotifidentifier/_src/wc.py
chemicalmotifidentifier-0.0.9.dist-info/METADATA
chemicalmotifidentifier-0.0.9.dist-info/WHEEL
chemicalmotifidentifier-0.0.9.dist-info/top_level.txt
chemicalmotifidentifier-0.0.9.dist-info/RECORD
