Metadata-Version: 2.1
Name: chemicalmotifidentifier
Version: 0.0.9
Summary: Chemical Motif Identifier
Home-page: https://github.com/killiansheriff/ChemicalMotifIdentifier
Author: Killian Sheriff
Author-email: ksheriff@mit.edu
Requires-Dist: e3nn
Requires-Dist: matplotlib
Requires-Dist: networkx
Requires-Dist: numpy
Requires-Dist: ovito
Requires-Dist: pandas
Requires-Dist: scikit-learn
Requires-Dist: scipy
Requires-Dist: tqdm
Requires-Dist: NshellFinder
Requires-Dist: polyaenum
Requires-Dist: nsimplex
Requires-Dist: lovelyplots
